{"ATLAS":{"SPRITES":[{"SPRITE":{"name":"0000","x":4361,"y":1405,"w":46,"h":127,"rotated":false}},{"SPRITE":{"name":"0001","x":4361,"y":1405,"w":46,"h":127,"rotated":false}},{"SPRITE":{"name":"0002","x":5587,"y":1499,"w":42,"h":68,"rotated":false}},{"SPRITE":{"name":"0003","x":527,"y":2447,"w":38,"h":85,"rotated":false}},{"SPRITE":{"name":"0004","x":527,"y":2447,"w":38,"h":85,"rotated":false}},{"SPRITE":{"name":"0005","x":2055,"y":901,"w":28,"h":119,"rotated":false}},{"SPRITE":{"name":"0006","x":2055,"y":901,"w":28,"h":119,"rotated":false}},{"SPRITE":{"name":"0007","x":1146,"y":2386,"w":35,"h":108,"rotated":false}},{"SPRITE":{"name":"0008","x":2802,"y":829,"w":161,"h":98,"rotated":false}},{"SPRITE":{"name":"0009","x":4626,"y":4022,"w":201,"h":184,"rotated":false}},{"SPRITE":{"name":"0010","x":5135,"y":4245,"w":180,"h":112,"rotated":false}},{"SPRITE":{"name":"0011","x":5135,"y":4245,"w":180,"h":112,"rotated":false}},{"SPRITE":{"name":"0012","x":1210,"y":1530,"w":304,"h":434,"rotated":false}},{"SPRITE":{"name":"0013","x":7599,"y":3921,"w":369,"h":234,"rotated":false}},{"SPRITE":{"name":"0014","x":1755,"y":4083,"w":325,"h":222,"rotated":false}},{"SPRITE":{"name":"0015","x":1755,"y":4083,"w":325,"h":222,"rotated":false}},{"SPRITE":{"name":"0016","x":3558,"y":4011,"w":341,"h":218,"rotated":false}},{"SPRITE":{"name":"0017","x":3499,"y":3532,"w":440,"h":479,"rotated":false}},{"SPRITE":{"name":"0018","x":5372,"y":3531,"w":441,"h":490,"rotated":false}},{"SPRITE":{"name":"0019","x":5561,"y":4021,"w":169,"h":236,"rotated":false}},{"SPRITE":{"name":"0020","x":2200,"y":2839,"w":510,"h":650,"rotated":false}},{"SPRITE":{"name":"0021","x":2200,"y":2839,"w":510,"h":650,"rotated":false}},{"SPRITE":{"name":"0022","x":0,"y":2232,"w":527,"h":648,"rotated":false}},{"SPRITE":{"name":"0023","x":5315,"y":4245,"w":177,"h":113,"rotated":false}},{"SPRITE":{"name":"0024","x":5315,"y":4245,"w":177,"h":113,"rotated":false}},{"SPRITE":{"name":"0025","x":632,"y":4245,"w":182,"h":122,"rotated":false}},{"SPRITE":{"name":"0026","x":632,"y":4245,"w":182,"h":122,"rotated":false}},{"SPRITE":{"name":"0027","x":632,"y":4245,"w":182,"h":122,"rotated":false}},{"SPRITE":{"name":"0028","x":6775,"y":1779,"w":55,"h":95,"rotated":false}},{"SPRITE":{"name":"0029","x":4361,"y":1133,"w":69,"h":102,"rotated":false}},{"SPRITE":{"name":"0030","x":610,"y":1407,"w":46,"h":122,"rotated":false}},{"SPRITE":{"name":"0031","x":6712,"y":2273,"w":32,"h":129,"rotated":false}},{"SPRITE":{"name":"0032","x":6712,"y":2273,"w":32,"h":129,"rotated":false}},{"SPRITE":{"name":"0033","x":8155,"y":263,"w":29,"h":144,"rotated":false}},{"SPRITE":{"name":"0034","x":8155,"y":263,"w":29,"h":144,"rotated":false}},{"SPRITE":{"name":"0035","x":4407,"y":1405,"w":33,"h":96,"rotated":false}},{"SPRITE":{"name":"0036","x":4407,"y":1405,"w":33,"h":96,"rotated":false}},{"SPRITE":{"name":"0037","x":3126,"y":744,"w":53,"h":81,"rotated":false}},{"SPRITE":{"name":"0038","x":2353,"y":1517,"w":80,"h":37,"rotated":false}},{"SPRITE":{"name":"0039","x":2628,"y":931,"w":716,"h":650,"rotated":false}},{"SPRITE":{"name":"0040","x":4441,"y":0,"w":701,"h":763,"rotated":false}},{"SPRITE":{"name":"0041","x":0,"y":908,"w":610,"h":694,"rotated":false}},{"SPRITE":{"name":"0042","x":1210,"y":2135,"w":559,"h":626,"rotated":false}},{"SPRITE":{"name":"0043","x":4975,"y":2853,"w":598,"h":495,"rotated":false}},{"SPRITE":{"name":"0044","x":2628,"y":565,"w":498,"h":264,"rotated":false}},{"SPRITE":{"name":"0045","x":972,"y":4084,"w":372,"h":189,"rotated":false}},{"SPRITE":{"name":"0046","x":1409,"y":3982,"w":346,"h":225,"rotated":false}},{"SPRITE":{"name":"0047","x":1409,"y":3982,"w":346,"h":225,"rotated":false}},{"SPRITE":{"name":"0048","x":2328,"y":2618,"w":365,"h":205,"rotated":false}},{"SPRITE":{"name":"0049","x":2328,"y":2618,"w":365,"h":205,"rotated":false}},{"SPRITE":{"name":"0050","x":3939,"y":3875,"w":355,"h":248,"rotated":false}},{"SPRITE":{"name":"0051","x":2617,"y":3977,"w":355,"h":226,"rotated":false}},{"SPRITE":{"name":"0052","x":3899,"y":4123,"w":330,"h":193,"rotated":false}},{"SPRITE":{"name":"0053","x":6849,"y":3180,"w":396,"h":631,"rotated":false}},{"SPRITE":{"name":"0054","x":3940,"y":966,"w":421,"h":646,"rotated":false}},{"SPRITE":{"name":"0055","x":3940,"y":966,"w":421,"h":646,"rotated":false}},{"SPRITE":{"name":"0056","x":6444,"y":3124,"w":405,"h":634,"rotated":false}},{"SPRITE":{"name":"0057","x":6444,"y":3124,"w":405,"h":634,"rotated":false}},{"SPRITE":{"name":"0058","x":6444,"y":3124,"w":405,"h":634,"rotated":false}},{"SPRITE":{"name":"0059","x":6444,"y":3124,"w":405,"h":634,"rotated":false}},{"SPRITE":{"name":"0060","x":6444,"y":3124,"w":405,"h":634,"rotated":false}},{"SPRITE":{"name":"0061","x":6444,"y":3124,"w":405,"h":634,"rotated":false}},{"SPRITE":{"name":"0062","x":4971,"y":3348,"w":401,"h":618,"rotated":false}},{"SPRITE":{"name":"0063","x":1883,"y":3489,"w":392,"h":594,"rotated":false}},{"SPRITE":{"name":"0064","x":6444,"y":2912,"w":265,"h":202,"rotated":false}},{"SPRITE":{"name":"0065","x":7599,"y":4155,"w":234,"h":145,"rotated":false}},{"SPRITE":{"name":"0066","x":358,"y":4099,"w":274,"h":235,"rotated":false}},{"SPRITE":{"name":"0067","x":358,"y":4099,"w":274,"h":235,"rotated":false}},{"SPRITE":{"name":"0068","x":5121,"y":2197,"w":528,"h":656,"rotated":false}},{"SPRITE":{"name":"0069","x":5121,"y":2197,"w":528,"h":656,"rotated":false}},{"SPRITE":{"name":"0070","x":5649,"y":2197,"w":531,"h":652,"rotated":false}},{"SPRITE":{"name":"0071","x":5649,"y":2197,"w":531,"h":652,"rotated":false}},{"SPRITE":{"name":"0072","x":5649,"y":2197,"w":531,"h":652,"rotated":false}},{"SPRITE":{"name":"0073","x":5649,"y":2197,"w":531,"h":652,"rotated":false}},{"SPRITE":{"name":"0074","x":4970,"y":4189,"w":165,"h":194,"rotated":false}},{"SPRITE":{"name":"0075","x":4970,"y":4189,"w":165,"h":194,"rotated":false}},{"SPRITE":{"name":"0076","x":5912,"y":4181,"w":160,"h":202,"rotated":false}},{"SPRITE":{"name":"0077","x":5912,"y":4181,"w":160,"h":202,"rotated":false}},{"SPRITE":{"name":"0078","x":7613,"y":3243,"w":367,"h":678,"rotated":false}},{"SPRITE":{"name":"0079","x":7245,"y":3180,"w":368,"h":678,"rotated":false}},{"SPRITE":{"name":"0080","x":7245,"y":3180,"w":368,"h":678,"rotated":false}},{"SPRITE":{"name":"0081","x":5813,"y":3952,"w":329,"h":229,"rotated":false}},{"SPRITE":{"name":"0082","x":5813,"y":3952,"w":329,"h":229,"rotated":false}},{"SPRITE":{"name":"0083","x":4294,"y":4033,"w":332,"h":220,"rotated":false}},{"SPRITE":{"name":"0084","x":4294,"y":4033,"w":332,"h":220,"rotated":false}},{"SPRITE":{"name":"0085","x":5230,"y":4021,"w":331,"h":224,"rotated":false}},{"SPRITE":{"name":"0086","x":5230,"y":4021,"w":331,"h":224,"rotated":false}},{"SPRITE":{"name":"0087","x":5230,"y":4021,"w":331,"h":224,"rotated":false}},{"SPRITE":{"name":"0088","x":5230,"y":4021,"w":331,"h":224,"rotated":false}},{"SPRITE":{"name":"0089","x":7842,"y":424,"w":340,"h":179,"rotated":false}},{"SPRITE":{"name":"0090","x":656,"y":1407,"w":55,"h":101,"rotated":false}},{"SPRITE":{"name":"0091","x":656,"y":1407,"w":55,"h":101,"rotated":false}},{"SPRITE":{"name":"0092","x":2072,"y":2135,"w":47,"h":83,"rotated":false}},{"SPRITE":{"name":"0093","x":2072,"y":2135,"w":47,"h":83,"rotated":false}},{"SPRITE":{"name":"0094","x":527,"y":2232,"w":43,"h":119,"rotated":false}},{"SPRITE":{"name":"0095","x":527,"y":2232,"w":43,"h":119,"rotated":false}},{"SPRITE":{"name":"0096","x":1146,"y":2267,"w":40,"h":119,"rotated":false}},{"SPRITE":{"name":"0097","x":1146,"y":2267,"w":40,"h":119,"rotated":false}},{"SPRITE":{"name":"0098","x":2249,"y":1517,"w":104,"h":50,"rotated":false}},{"SPRITE":{"name":"0099","x":4996,"y":966,"w":591,"h":686,"rotated":false}},{"SPRITE":{"name":"0100","x":4996,"y":966,"w":591,"h":686,"rotated":false}},{"SPRITE":{"name":"0101","x":3344,"y":966,"w":596,"h":686,"rotated":false}},{"SPRITE":{"name":"0102","x":6241,"y":961,"w":599,"h":686,"rotated":false}},{"SPRITE":{"name":"0103","x":6142,"y":3993,"w":255,"h":222,"rotated":false}},{"SPRITE":{"name":"0104","x":7127,"y":3858,"w":236,"h":392,"rotated":false}},{"SPRITE":{"name":"0105","x":7363,"y":3858,"w":236,"h":392,"rotated":false}},{"SPRITE":{"name":"0106","x":1769,"y":2135,"w":187,"h":66,"rotated":false}},{"SPRITE":{"name":"0107","x":6840,"y":1196,"w":120,"h":50,"rotated":false}},{"SPRITE":{"name":"0108","x":5587,"y":1299,"w":92,"h":77,"rotated":false}},{"SPRITE":{"name":"0109","x":2137,"y":1517,"w":112,"h":48,"rotated":false}},{"SPRITE":{"name":"0110","x":6241,"y":896,"w":126,"h":59,"rotated":false}},{"SPRITE":{"name":"0111","x":4361,"y":1235,"w":80,"h":87,"rotated":false}},{"SPRITE":{"name":"0112","x":2663,"y":2336,"w":39,"h":103,"rotated":false}},{"SPRITE":{"name":"0113","x":2663,"y":2336,"w":39,"h":103,"rotated":false}},{"SPRITE":{"name":"0114","x":8155,"y":139,"w":37,"h":124,"rotated":false}},{"SPRITE":{"name":"0115","x":8155,"y":139,"w":37,"h":124,"rotated":false}},{"SPRITE":{"name":"0116","x":1452,"y":1964,"w":50,"h":111,"rotated":false}},{"SPRITE":{"name":"0117","x":1146,"y":2156,"w":50,"h":111,"rotated":false}},{"SPRITE":{"name":"0118","x":2080,"y":4083,"w":186,"h":188,"rotated":false}},{"SPRITE":{"name":"0119","x":5730,"y":4181,"w":182,"h":183,"rotated":false}},{"SPRITE":{"name":"0120","x":5730,"y":4181,"w":182,"h":183,"rotated":false}},{"SPRITE":{"name":"0121","x":7842,"y":0,"w":313,"h":424,"rotated":false}},{"SPRITE":{"name":"0122","x":7842,"y":0,"w":313,"h":424,"rotated":false}},{"SPRITE":{"name":"0123","x":3280,"y":4011,"w":278,"h":268,"rotated":false}},{"SPRITE":{"name":"0124","x":3280,"y":4011,"w":278,"h":268,"rotated":false}},{"SPRITE":{"name":"0125","x":2972,"y":4023,"w":275,"h":269,"rotated":false}},{"SPRITE":{"name":"0126","x":2972,"y":4023,"w":275,"h":269,"rotated":false}},{"SPRITE":{"name":"0127","x":2972,"y":4023,"w":275,"h":269,"rotated":false}},{"SPRITE":{"name":"0128","x":2972,"y":4023,"w":275,"h":269,"rotated":false}},{"SPRITE":{"name":"0129","x":0,"y":1602,"w":590,"h":630,"rotated":false}},{"SPRITE":{"name":"0130","x":6775,"y":1879,"w":605,"h":601,"rotated":false}},{"SPRITE":{"name":"0131","x":6775,"y":1879,"w":605,"h":601,"rotated":false}},{"SPRITE":{"name":"0132","x":3311,"y":1652,"w":601,"h":616,"rotated":false}},{"SPRITE":{"name":"0133","x":3940,"y":1618,"w":601,"h":618,"rotated":false}},{"SPRITE":{"name":"0134","x":3940,"y":1618,"w":601,"h":618,"rotated":false}},{"SPRITE":{"name":"0135","x":3940,"y":1618,"w":601,"h":618,"rotated":false}},{"SPRITE":{"name":"0136","x":3940,"y":1618,"w":601,"h":618,"rotated":false}},{"SPRITE":{"name":"0137","x":610,"y":1530,"w":600,"h":626,"rotated":false}},{"SPRITE":{"name":"0138","x":610,"y":1530,"w":600,"h":626,"rotated":false}},{"SPRITE":{"name":"0139","x":2719,"y":1581,"w":592,"h":628,"rotated":false}},{"SPRITE":{"name":"0140","x":2275,"y":3535,"w":461,"h":442,"rotated":false}},{"SPRITE":{"name":"0141","x":1409,"y":3482,"w":474,"h":500,"rotated":false}},{"SPRITE":{"name":"0142","x":3499,"y":2906,"w":245,"h":427,"rotated":false}},{"SPRITE":{"name":"0143","x":1769,"y":2225,"w":559,"h":614,"rotated":false}},{"SPRITE":{"name":"0144","x":1529,"y":901,"w":526,"h":612,"rotated":false}},{"SPRITE":{"name":"0145","x":1529,"y":901,"w":526,"h":612,"rotated":false}},{"SPRITE":{"name":"0146","x":3265,"y":2268,"w":533,"h":638,"rotated":false}},{"SPRITE":{"name":"0147","x":3265,"y":2268,"w":533,"h":638,"rotated":false}},{"SPRITE":{"name":"0148","x":3265,"y":2268,"w":533,"h":638,"rotated":false}},{"SPRITE":{"name":"0149","x":3265,"y":2268,"w":533,"h":638,"rotated":false}},{"SPRITE":{"name":"0150","x":6180,"y":2273,"w":532,"h":639,"rotated":false}},{"SPRITE":{"name":"0151","x":6180,"y":2273,"w":532,"h":639,"rotated":false}},{"SPRITE":{"name":"0152","x":7238,"y":2538,"w":527,"h":642,"rotated":false}},{"SPRITE":{"name":"0153","x":6367,"y":896,"w":80,"h":45,"rotated":false}},{"SPRITE":{"name":"0154","x":6367,"y":896,"w":80,"h":45,"rotated":false}},{"SPRITE":{"name":"0155","x":5093,"y":900,"w":34,"h":61,"rotated":false}},{"SPRITE":{"name":"0156","x":2663,"y":2439,"w":39,"h":91,"rotated":false}},{"SPRITE":{"name":"0157","x":8155,"y":0,"w":37,"h":139,"rotated":false}},{"SPRITE":{"name":"0158","x":8155,"y":0,"w":37,"h":139,"rotated":false}},{"SPRITE":{"name":"0159","x":6775,"y":1647,"w":44,"h":132,"rotated":false}},{"SPRITE":{"name":"0160","x":6775,"y":1647,"w":44,"h":132,"rotated":false}},{"SPRITE":{"name":"0161","x":527,"y":2351,"w":41,"h":96,"rotated":false}},{"SPRITE":{"name":"0162","x":527,"y":2351,"w":41,"h":96,"rotated":false}},{"SPRITE":{"name":"0163","x":1529,"y":1517,"w":608,"h":618,"rotated":false}},{"SPRITE":{"name":"0164","x":6840,"y":1252,"w":608,"h":627,"rotated":false}},{"SPRITE":{"name":"0165","x":6840,"y":1252,"w":608,"h":627,"rotated":false}},{"SPRITE":{"name":"0166","x":4848,"y":3966,"w":382,"h":223,"rotated":false}},{"SPRITE":{"name":"0167","x":590,"y":2156,"w":556,"h":624,"rotated":false}},{"SPRITE":{"name":"0168","x":590,"y":2156,"w":556,"h":624,"rotated":false}},{"SPRITE":{"name":"0169","x":7380,"y":1896,"w":550,"h":642,"rotated":false}},{"SPRITE":{"name":"0170","x":2719,"y":2209,"w":546,"h":634,"rotated":false}},{"SPRITE":{"name":"0171","x":2719,"y":2209,"w":546,"h":634,"rotated":false}},{"SPRITE":{"name":"0172","x":5813,"y":3618,"w":336,"h":334,"rotated":false}},{"SPRITE":{"name":"0173","x":0,"y":3614,"w":336,"h":360,"rotated":false}},{"SPRITE":{"name":"0174","x":7980,"y":3688,"w":173,"h":218,"rotated":false}},{"SPRITE":{"name":"0175","x":6840,"y":961,"w":157,"h":235,"rotated":false}},{"SPRITE":{"name":"0176","x":6840,"y":961,"w":157,"h":235,"rotated":false}},{"SPRITE":{"name":"0177","x":8034,"y":1484,"w":152,"h":225,"rotated":false}},{"SPRITE":{"name":"0178","x":8034,"y":1484,"w":152,"h":225,"rotated":false}},{"SPRITE":{"name":"0179","x":375,"y":2880,"w":149,"h":225,"rotated":false}},{"SPRITE":{"name":"0180","x":375,"y":2880,"w":149,"h":225,"rotated":false}},{"SPRITE":{"name":"0181","x":375,"y":2880,"w":149,"h":225,"rotated":false}},{"SPRITE":{"name":"0182","x":375,"y":2880,"w":149,"h":225,"rotated":false}},{"SPRITE":{"name":"0183","x":375,"y":2880,"w":149,"h":225,"rotated":false}},{"SPRITE":{"name":"0184","x":4975,"y":2521,"w":146,"h":225,"rotated":false}},{"SPRITE":{"name":"0185","x":4975,"y":2521,"w":146,"h":225,"rotated":false}},{"SPRITE":{"name":"0186","x":4827,"y":4189,"w":143,"h":225,"rotated":false}},{"SPRITE":{"name":"0187","x":6149,"y":3618,"w":261,"h":375,"rotated":false}},{"SPRITE":{"name":"0188","x":6888,"y":3811,"w":239,"h":392,"rotated":false}},{"SPRITE":{"name":"0189","x":4609,"y":3619,"w":239,"h":403,"rotated":false}},{"SPRITE":{"name":"0190","x":4609,"y":3619,"w":239,"h":403,"rotated":false}},{"SPRITE":{"name":"0191","x":3041,"y":3621,"w":239,"h":402,"rotated":false}},{"SPRITE":{"name":"0192","x":3041,"y":3621,"w":239,"h":402,"rotated":false}},{"SPRITE":{"name":"0193","x":3041,"y":3621,"w":239,"h":402,"rotated":false}},{"SPRITE":{"name":"0194","x":3041,"y":3621,"w":239,"h":402,"rotated":false}},{"SPRITE":{"name":"0195","x":3041,"y":3621,"w":239,"h":402,"rotated":false}},{"SPRITE":{"name":"0196","x":6410,"y":3758,"w":239,"h":401,"rotated":false}},{"SPRITE":{"name":"0197","x":6410,"y":3758,"w":239,"h":401,"rotated":false}},{"SPRITE":{"name":"0198","x":6649,"y":3811,"w":239,"h":399,"rotated":false}},{"SPRITE":{"name":"0199","x":6063,"y":2912,"w":381,"h":706,"rotated":false}},{"SPRITE":{"name":"0200","x":0,"y":2880,"w":375,"h":734,"rotated":false}},{"SPRITE":{"name":"0201","x":0,"y":2880,"w":375,"h":734,"rotated":false}},{"SPRITE":{"name":"0202","x":4217,"y":2931,"w":390,"h":663,"rotated":false}},{"SPRITE":{"name":"0203","x":4217,"y":2931,"w":390,"h":663,"rotated":false}},{"SPRITE":{"name":"0204","x":4607,"y":2931,"w":364,"h":688,"rotated":false}},{"SPRITE":{"name":"0205","x":4607,"y":2931,"w":364,"h":688,"rotated":false}},{"SPRITE":{"name":"0206","x":4607,"y":2931,"w":364,"h":688,"rotated":false}},{"SPRITE":{"name":"0207","x":4607,"y":2931,"w":364,"h":688,"rotated":false}},{"SPRITE":{"name":"0208","x":4607,"y":2931,"w":364,"h":688,"rotated":false}},{"SPRITE":{"name":"0209","x":1049,"y":3400,"w":360,"h":684,"rotated":false}},{"SPRITE":{"name":"0210","x":1049,"y":3400,"w":360,"h":684,"rotated":false}},{"SPRITE":{"name":"0211","x":375,"y":3427,"w":358,"h":672,"rotated":false}},{"SPRITE":{"name":"0212","x":3181,"y":0,"w":649,"h":931,"rotated":false}},{"SPRITE":{"name":"0213","x":7813,"y":616,"w":353,"h":633,"rotated":false}},{"SPRITE":{"name":"0214","x":5121,"y":1652,"w":460,"h":497,"rotated":false}},{"SPRITE":{"name":"0215","x":527,"y":2780,"w":522,"h":647,"rotated":false}},{"SPRITE":{"name":"0216","x":3119,"y":2906,"w":380,"h":715,"rotated":false}},{"SPRITE":{"name":"0217","x":3119,"y":2906,"w":380,"h":715,"rotated":false}},{"SPRITE":{"name":"0218","x":7765,"y":2538,"w":404,"h":705,"rotated":false}},{"SPRITE":{"name":"0219","x":7765,"y":2538,"w":404,"h":705,"rotated":false}},{"SPRITE":{"name":"0220","x":2710,"y":2843,"w":409,"h":692,"rotated":false}},{"SPRITE":{"name":"0221","x":2710,"y":2843,"w":409,"h":692,"rotated":false}},{"SPRITE":{"name":"0222","x":2710,"y":2843,"w":409,"h":692,"rotated":false}},{"SPRITE":{"name":"0223","x":2710,"y":2843,"w":409,"h":692,"rotated":false}},{"SPRITE":{"name":"0224","x":2710,"y":2843,"w":409,"h":692,"rotated":false}},{"SPRITE":{"name":"0225","x":5649,"y":2849,"w":414,"h":682,"rotated":false}},{"SPRITE":{"name":"0226","x":5649,"y":2849,"w":414,"h":682,"rotated":false}},{"SPRITE":{"name":"0227","x":3798,"y":2873,"w":419,"h":659,"rotated":false}},{"SPRITE":{"name":"0228","x":610,"y":908,"w":73,"h":215,"rotated":false}},{"SPRITE":{"name":"0229","x":4996,"y":763,"w":97,"h":173,"rotated":false}},{"SPRITE":{"name":"0230","x":4996,"y":763,"w":97,"h":173,"rotated":false}},{"SPRITE":{"name":"0231","x":4361,"y":1532,"w":77,"h":67,"rotated":false}},{"SPRITE":{"name":"0232","x":4361,"y":1532,"w":77,"h":67,"rotated":false}},{"SPRITE":{"name":"0233","x":3126,"y":565,"w":46,"h":179,"rotated":false}},{"SPRITE":{"name":"0234","x":3126,"y":565,"w":46,"h":179,"rotated":false}},{"SPRITE":{"name":"0235","x":4361,"y":966,"w":56,"h":167,"rotated":false}},{"SPRITE":{"name":"0236","x":4361,"y":966,"w":56,"h":167,"rotated":false}},{"SPRITE":{"name":"0237","x":4361,"y":966,"w":56,"h":167,"rotated":false}},{"SPRITE":{"name":"0238","x":5587,"y":1376,"w":50,"h":123,"rotated":false}},{"SPRITE":{"name":"0239","x":5587,"y":1376,"w":50,"h":123,"rotated":false}},{"SPRITE":{"name":"0240","x":5587,"y":1203,"w":96,"h":96,"rotated":false}},{"SPRITE":{"name":"0241","x":4374,"y":3619,"w":235,"h":414,"rotated":false}},{"SPRITE":{"name":"0242","x":5372,"y":3348,"w":215,"h":170,"rotated":false}},{"SPRITE":{"name":"0243","x":7930,"y":1896,"w":235,"h":487,"rotated":false}},{"SPRITE":{"name":"0244","x":7245,"y":3180,"w":368,"h":678,"rotated":false}},{"SPRITE":{"name":"0245","x":7245,"y":3180,"w":368,"h":678,"rotated":false}},{"SPRITE":{"name":"0246","x":5813,"y":3952,"w":329,"h":229,"rotated":false}},{"SPRITE":{"name":"0247","x":5813,"y":3952,"w":329,"h":229,"rotated":false}},{"SPRITE":{"name":"0248","x":4294,"y":4033,"w":332,"h":220,"rotated":false}},{"SPRITE":{"name":"0249","x":4294,"y":4033,"w":332,"h":220,"rotated":false}},{"SPRITE":{"name":"0250","x":5230,"y":4021,"w":331,"h":224,"rotated":false}},{"SPRITE":{"name":"0251","x":5230,"y":4021,"w":331,"h":224,"rotated":false}},{"SPRITE":{"name":"0252","x":5230,"y":4021,"w":331,"h":224,"rotated":false}},{"SPRITE":{"name":"0253","x":5230,"y":4021,"w":331,"h":224,"rotated":false}},{"SPRITE":{"name":"0254","x":7842,"y":424,"w":340,"h":179,"rotated":false}},{"SPRITE":{"name":"0255","x":656,"y":1407,"w":55,"h":101,"rotated":false}},{"SPRITE":{"name":"0256","x":656,"y":1407,"w":55,"h":101,"rotated":false}},{"SPRITE":{"name":"0257","x":2072,"y":2135,"w":47,"h":83,"rotated":false}},{"SPRITE":{"name":"0258","x":2072,"y":2135,"w":47,"h":83,"rotated":false}},{"SPRITE":{"name":"0259","x":527,"y":2232,"w":43,"h":119,"rotated":false}},{"SPRITE":{"name":"0260","x":527,"y":2232,"w":43,"h":119,"rotated":false}},{"SPRITE":{"name":"0261","x":1146,"y":2267,"w":40,"h":119,"rotated":false}},{"SPRITE":{"name":"0262","x":1146,"y":2267,"w":40,"h":119,"rotated":false}},{"SPRITE":{"name":"0263","x":2249,"y":1517,"w":104,"h":50,"rotated":false}},{"SPRITE":{"name":"0264","x":4996,"y":966,"w":591,"h":686,"rotated":false}},{"SPRITE":{"name":"0265","x":4996,"y":966,"w":591,"h":686,"rotated":false}},{"SPRITE":{"name":"0266","x":6241,"y":961,"w":599,"h":686,"rotated":false}},{"SPRITE":{"name":"0267","x":6397,"y":4159,"w":151,"h":222,"rotated":false}},{"SPRITE":{"name":"0268","x":6397,"y":4159,"w":151,"h":222,"rotated":false}},{"SPRITE":{"name":"0269","x":375,"y":3105,"w":149,"h":225,"rotated":false}},{"SPRITE":{"name":"0270","x":375,"y":3105,"w":149,"h":225,"rotated":false}},{"SPRITE":{"name":"0271","x":6888,"y":3811,"w":239,"h":392,"rotated":false}},{"SPRITE":{"name":"0272","x":6888,"y":3811,"w":239,"h":392,"rotated":false}},{"SPRITE":{"name":"0273","x":733,"y":3853,"w":239,"h":392,"rotated":false}},{"SPRITE":{"name":"0274","x":733,"y":3853,"w":239,"h":392,"rotated":false}},{"SPRITE":{"name":"0275","x":1409,"y":3400,"w":187,"h":66,"rotated":false}},{"SPRITE":{"name":"0276","x":1956,"y":2135,"w":116,"h":78,"rotated":false}},{"SPRITE":{"name":"0277","x":5587,"y":1299,"w":92,"h":77,"rotated":false}},{"SPRITE":{"name":"0278","x":4361,"y":1322,"w":80,"h":83,"rotated":false}},{"SPRITE":{"name":"0279","x":610,"y":1239,"w":83,"h":98,"rotated":false}},{"SPRITE":{"name":"0280","x":5637,"y":1376,"w":42,"h":145,"rotated":false}},{"SPRITE":{"name":"0281","x":5637,"y":1376,"w":42,"h":145,"rotated":false}},{"SPRITE":{"name":"0282","x":5093,"y":763,"w":46,"h":137,"rotated":false}},{"SPRITE":{"name":"0283","x":5093,"y":763,"w":46,"h":137,"rotated":false}},{"SPRITE":{"name":"0284","x":2663,"y":2225,"w":50,"h":111,"rotated":false}},{"SPRITE":{"name":"0285","x":2663,"y":2225,"w":50,"h":111,"rotated":false}},{"SPRITE":{"name":"0286","x":3558,"y":4229,"w":167,"h":162,"rotated":false}},{"SPRITE":{"name":"0287","x":2617,"y":4203,"w":142,"h":221,"rotated":false}},{"SPRITE":{"name":"0288","x":2617,"y":4203,"w":142,"h":221,"rotated":false}},{"SPRITE":{"name":"0289","x":8034,"y":1249,"w":151,"h":235,"rotated":false}},{"SPRITE":{"name":"0290","x":8034,"y":1249,"w":151,"h":235,"rotated":false}},{"SPRITE":{"name":"0291","x":4975,"y":2287,"w":144,"h":234,"rotated":false}},{"SPRITE":{"name":"0292","x":4975,"y":2287,"w":144,"h":234,"rotated":false}},{"SPRITE":{"name":"0293","x":4975,"y":2287,"w":144,"h":234,"rotated":false}},{"SPRITE":{"name":"0294","x":4975,"y":2287,"w":144,"h":234,"rotated":false}},{"SPRITE":{"name":"0295","x":2759,"y":4203,"w":162,"h":189,"rotated":false}},{"SPRITE":{"name":"0296","x":2759,"y":4203,"w":162,"h":189,"rotated":false}},{"SPRITE":{"name":"0297","x":7842,"y":0,"w":313,"h":424,"rotated":false}},{"SPRITE":{"name":"0298","x":7842,"y":0,"w":313,"h":424,"rotated":false}},{"SPRITE":{"name":"0299","x":733,"y":3427,"w":307,"h":426,"rotated":false}},{"SPRITE":{"name":"0300","x":733,"y":3427,"w":307,"h":426,"rotated":false}},{"SPRITE":{"name":"0301","x":0,"y":3974,"w":358,"h":229,"rotated":false}},{"SPRITE":{"name":"0302","x":0,"y":3974,"w":358,"h":229,"rotated":false}},{"SPRITE":{"name":"0303","x":7968,"y":3921,"w":223,"h":284,"rotated":false}},{"SPRITE":{"name":"0304","x":0,"y":1602,"w":590,"h":630,"rotated":false}},{"SPRITE":{"name":"0305","x":6775,"y":1879,"w":605,"h":601,"rotated":false}},{"SPRITE":{"name":"0306","x":6775,"y":1879,"w":605,"h":601,"rotated":false}},{"SPRITE":{"name":"0307","x":3940,"y":1618,"w":601,"h":618,"rotated":false}},{"SPRITE":{"name":"0308","x":3940,"y":1618,"w":601,"h":618,"rotated":false}},{"SPRITE":{"name":"0309","x":3940,"y":1618,"w":601,"h":618,"rotated":false}},{"SPRITE":{"name":"0310","x":3940,"y":1618,"w":601,"h":618,"rotated":false}},{"SPRITE":{"name":"0311","x":6182,"y":1647,"w":593,"h":626,"rotated":false}},{"SPRITE":{"name":"0312","x":6182,"y":1647,"w":593,"h":626,"rotated":false}},{"SPRITE":{"name":"0313","x":2275,"y":3535,"w":461,"h":442,"rotated":false}},{"SPRITE":{"name":"0314","x":2275,"y":3977,"w":342,"h":238,"rotated":false}},{"SPRITE":{"name":"0315","x":2328,"y":2225,"w":335,"h":393,"rotated":false}},{"SPRITE":{"name":"0316","x":2328,"y":2225,"w":335,"h":393,"rotated":false}},{"SPRITE":{"name":"0317","x":1769,"y":2225,"w":559,"h":614,"rotated":false}},{"SPRITE":{"name":"0318","x":1529,"y":901,"w":526,"h":612,"rotated":false}},{"SPRITE":{"name":"0319","x":1529,"y":901,"w":526,"h":612,"rotated":false}},{"SPRITE":{"name":"0320","x":3265,"y":2268,"w":533,"h":638,"rotated":false}},{"SPRITE":{"name":"0321","x":3265,"y":2268,"w":533,"h":638,"rotated":false}},{"SPRITE":{"name":"0322","x":3265,"y":2268,"w":533,"h":638,"rotated":false}},{"SPRITE":{"name":"0323","x":3265,"y":2268,"w":533,"h":638,"rotated":false}},{"SPRITE":{"name":"0324","x":1146,"y":2761,"w":529,"h":639,"rotated":false}},{"SPRITE":{"name":"0325","x":1146,"y":2761,"w":529,"h":639,"rotated":false}},{"SPRITE":{"name":"0326","x":4441,"y":763,"w":555,"h":855,"rotated":false}},{"SPRITE":{"name":"0327","x":4441,"y":763,"w":555,"h":855,"rotated":false}},{"SPRITE":{"name":"0328","x":5684,"y":674,"w":557,"h":893,"rotated":false}},{"SPRITE":{"name":"0329","x":5684,"y":674,"w":557,"h":893,"rotated":false}},{"SPRITE":{"name":"0330","x":2086,"y":565,"w":542,"h":952,"rotated":false}},{"SPRITE":{"name":"0331","x":2086,"y":565,"w":542,"h":952,"rotated":false}},{"SPRITE":{"name":"0332","x":6460,"y":0,"w":542,"h":961,"rotated":false}},{"SPRITE":{"name":"0333","x":6460,"y":0,"w":542,"h":961,"rotated":false}},{"SPRITE":{"name":"0334","x":5142,"y":0,"w":542,"h":966,"rotated":false}},{"SPRITE":{"name":"0335","x":5142,"y":0,"w":542,"h":966,"rotated":false}},{"SPRITE":{"name":"0336","x":3830,"y":0,"w":611,"h":966,"rotated":false}},{"SPRITE":{"name":"0337","x":3830,"y":0,"w":611,"h":966,"rotated":false}},{"SPRITE":{"name":"0338","x":1399,"y":0,"w":687,"h":901,"rotated":false}},{"SPRITE":{"name":"0339","x":712,"y":0,"w":687,"h":901,"rotated":false}},{"SPRITE":{"name":"0340","x":712,"y":0,"w":687,"h":901,"rotated":false}},{"SPRITE":{"name":"0341","x":712,"y":0,"w":687,"h":901,"rotated":false}},{"SPRITE":{"name":"0342","x":712,"y":0,"w":687,"h":901,"rotated":false}},{"SPRITE":{"name":"0343","x":712,"y":0,"w":687,"h":901,"rotated":false}},{"SPRITE":{"name":"0344","x":712,"y":0,"w":687,"h":901,"rotated":false}},{"SPRITE":{"name":"0345","x":712,"y":0,"w":687,"h":901,"rotated":false}},{"SPRITE":{"name":"0346","x":712,"y":0,"w":687,"h":901,"rotated":false}},{"SPRITE":{"name":"0347","x":712,"y":0,"w":687,"h":901,"rotated":false}},{"SPRITE":{"name":"0348","x":712,"y":0,"w":687,"h":901,"rotated":false}},{"SPRITE":{"name":"0349","x":0,"y":0,"w":712,"h":908,"rotated":false}},{"SPRITE":{"name":"0350","x":0,"y":0,"w":712,"h":908,"rotated":false}},{"SPRITE":{"name":"0351","x":2086,"y":0,"w":1095,"h":565,"rotated":false}},{"SPRITE":{"name":"0352","x":7930,"y":2383,"w":256,"h":135,"rotated":false}},{"SPRITE":{"name":"0353","x":1210,"y":1964,"w":242,"h":169,"rotated":false}},{"SPRITE":{"name":"0354","x":1210,"y":1964,"w":242,"h":169,"rotated":false}},{"SPRITE":{"name":"0355","x":0,"y":4203,"w":256,"h":124,"rotated":false}},{"SPRITE":{"name":"0356","x":0,"y":4203,"w":256,"h":124,"rotated":false}},{"SPRITE":{"name":"0357","x":3499,"y":3333,"w":247,"h":156,"rotated":false}},{"SPRITE":{"name":"0358","x":3499,"y":3333,"w":247,"h":156,"rotated":false}},{"SPRITE":{"name":"0359","x":6241,"y":674,"w":207,"h":222,"rotated":false}},{"SPRITE":{"name":"0360","x":6241,"y":674,"w":207,"h":222,"rotated":false}},{"SPRITE":{"name":"0361","x":2266,"y":4215,"w":260,"h":111,"rotated":false}},{"SPRITE":{"name":"0362","x":2266,"y":4215,"w":260,"h":111,"rotated":false}},{"SPRITE":{"name":"0363","x":6548,"y":4210,"w":259,"h":112,"rotated":false}},{"SPRITE":{"name":"0364","x":6548,"y":4210,"w":259,"h":112,"rotated":false}},{"SPRITE":{"name":"0365","x":7833,"y":4205,"w":260,"h":112,"rotated":false}},{"SPRITE":{"name":"0366","x":7833,"y":4205,"w":260,"h":112,"rotated":false}},{"SPRITE":{"name":"0367","x":7833,"y":4205,"w":260,"h":112,"rotated":false}},{"SPRITE":{"name":"0368","x":7833,"y":4205,"w":260,"h":112,"rotated":false}},{"SPRITE":{"name":"0369","x":7833,"y":4205,"w":260,"h":112,"rotated":false}},{"SPRITE":{"name":"0370","x":7833,"y":4205,"w":260,"h":112,"rotated":false}},{"SPRITE":{"name":"0371","x":7833,"y":4205,"w":260,"h":112,"rotated":false}},{"SPRITE":{"name":"0372","x":1344,"y":4207,"w":260,"h":112,"rotated":false}},{"SPRITE":{"name":"0373","x":375,"y":3330,"w":129,"h":96,"rotated":false}},{"SPRITE":{"name":"0374","x":375,"y":3330,"w":129,"h":96,"rotated":false}},{"SPRITE":{"name":"0375","x":1755,"y":3982,"w":126,"h":99,"rotated":false}},{"SPRITE":{"name":"0376","x":1755,"y":3982,"w":126,"h":99,"rotated":false}},{"SPRITE":{"name":"0377","x":3798,"y":2268,"w":109,"h":108,"rotated":false}},{"SPRITE":{"name":"0378","x":3798,"y":2268,"w":109,"h":108,"rotated":false}},{"SPRITE":{"name":"0379","x":4848,"y":3861,"w":119,"h":96,"rotated":false}},{"SPRITE":{"name":"0380","x":4848,"y":3737,"w":116,"h":124,"rotated":false}},{"SPRITE":{"name":"0381","x":4848,"y":3737,"w":116,"h":124,"rotated":false}},{"SPRITE":{"name":"0382","x":4848,"y":3619,"w":122,"h":118,"rotated":false}},{"SPRITE":{"name":"0383","x":4848,"y":3619,"w":122,"h":118,"rotated":false}},{"SPRITE":{"name":"0384","x":4848,"y":3619,"w":122,"h":118,"rotated":false}},{"SPRITE":{"name":"0385","x":2963,"y":829,"w":208,"h":74,"rotated":false}},{"SPRITE":{"name":"0386","x":7216,"y":4250,"w":165,"h":114,"rotated":false}},{"SPRITE":{"name":"0387","x":7216,"y":4250,"w":165,"h":114,"rotated":false}},{"SPRITE":{"name":"0388","x":6237,"y":4215,"w":157,"h":123,"rotated":false}},{"SPRITE":{"name":"0389","x":6237,"y":4215,"w":157,"h":123,"rotated":false}},{"SPRITE":{"name":"0390","x":6237,"y":4215,"w":157,"h":123,"rotated":false}},{"SPRITE":{"name":"0391","x":6237,"y":4215,"w":157,"h":123,"rotated":false}},{"SPRITE":{"name":"0392","x":7056,"y":4250,"w":160,"h":120,"rotated":false}},{"SPRITE":{"name":"0393","x":3725,"y":4229,"w":157,"h":123,"rotated":false}},{"SPRITE":{"name":"0394","x":3725,"y":4229,"w":157,"h":123,"rotated":false}},{"SPRITE":{"name":"0395","x":3725,"y":4229,"w":157,"h":123,"rotated":false}},{"SPRITE":{"name":"0396","x":3725,"y":4229,"w":157,"h":123,"rotated":false}},{"SPRITE":{"name":"0397","x":3725,"y":4229,"w":157,"h":123,"rotated":false}},{"SPRITE":{"name":"0398","x":2628,"y":829,"w":174,"h":94,"rotated":false}},{"SPRITE":{"name":"0399","x":7980,"y":3243,"w":194,"h":445,"rotated":false}},{"SPRITE":{"name":"0400","x":2137,"y":1581,"w":582,"h":644,"rotated":false}},{"SPRITE":{"name":"0401","x":2137,"y":1581,"w":582,"h":644,"rotated":false}},{"SPRITE":{"name":"0402","x":7448,"y":1252,"w":586,"h":644,"rotated":false}},{"SPRITE":{"name":"0403","x":7448,"y":1252,"w":586,"h":644,"rotated":false}},{"SPRITE":{"name":"0404","x":7448,"y":1252,"w":586,"h":644,"rotated":false}},{"SPRITE":{"name":"0405","x":7448,"y":1252,"w":586,"h":644,"rotated":false}},{"SPRITE":{"name":"0406","x":7448,"y":1252,"w":586,"h":644,"rotated":false}},{"SPRITE":{"name":"0407","x":7448,"y":1252,"w":586,"h":644,"rotated":false}},{"SPRITE":{"name":"0408","x":7448,"y":1252,"w":586,"h":644,"rotated":false}},{"SPRITE":{"name":"0409","x":7448,"y":1252,"w":586,"h":644,"rotated":false}},{"SPRITE":{"name":"0410","x":7448,"y":1252,"w":586,"h":644,"rotated":false}},{"SPRITE":{"name":"0411","x":7448,"y":1252,"w":586,"h":644,"rotated":false}},{"SPRITE":{"name":"0412","x":5587,"y":1567,"w":595,"h":630,"rotated":false}},{"SPRITE":{"name":"0413","x":2736,"y":3535,"w":305,"h":409,"rotated":false}},{"SPRITE":{"name":"0414","x":8184,"y":274,"w":6,"h":11,"rotated":false}},{"SPRITE":{"name":"0415","x":8184,"y":274,"w":6,"h":11,"rotated":false}},{"SPRITE":{"name":"0416","x":8184,"y":263,"w":6,"h":11,"rotated":false}},{"SPRITE":{"name":"0417","x":8184,"y":263,"w":6,"h":11,"rotated":false}},{"SPRITE":{"name":"0418","x":8184,"y":263,"w":6,"h":11,"rotated":false}},{"SPRITE":{"name":"0419","x":8184,"y":263,"w":6,"h":11,"rotated":false}},{"SPRITE":{"name":"0420","x":8184,"y":263,"w":6,"h":11,"rotated":false}},{"SPRITE":{"name":"0421","x":8184,"y":263,"w":6,"h":11,"rotated":false}},{"SPRITE":{"name":"0422","x":8184,"y":263,"w":6,"h":11,"rotated":false}},{"SPRITE":{"name":"0423","x":8184,"y":263,"w":6,"h":11,"rotated":false}},{"SPRITE":{"name":"0424","x":8184,"y":263,"w":6,"h":11,"rotated":false}},{"SPRITE":{"name":"0425","x":4448,"y":2287,"w":527,"h":644,"rotated":false}},{"SPRITE":{"name":"0426","x":4448,"y":2287,"w":527,"h":644,"rotated":false}},{"SPRITE":{"name":"0427","x":1675,"y":2839,"w":525,"h":643,"rotated":false}},{"SPRITE":{"name":"0428","x":1675,"y":2839,"w":525,"h":643,"rotated":false}},{"SPRITE":{"name":"0429","x":6712,"y":2480,"w":526,"h":644,"rotated":false}},{"SPRITE":{"name":"0430","x":6712,"y":2480,"w":526,"h":644,"rotated":false}},{"SPRITE":{"name":"0431","x":3280,"y":3858,"w":178,"h":136,"rotated":false}},{"SPRITE":{"name":"0432","x":1604,"y":4207,"w":126,"h":122,"rotated":false}},{"SPRITE":{"name":"0433","x":3798,"y":2376,"w":107,"h":107,"rotated":false}},{"SPRITE":{"name":"0434","x":5587,"y":1084,"w":92,"h":119,"rotated":false}},{"SPRITE":{"name":"0435","x":610,"y":1123,"w":99,"h":116,"rotated":false}},{"SPRITE":{"name":"0436","x":610,"y":1123,"w":99,"h":116,"rotated":false}},{"SPRITE":{"name":"0437","x":610,"y":1123,"w":99,"h":116,"rotated":false}},{"SPRITE":{"name":"0438","x":5587,"y":966,"w":94,"h":118,"rotated":false}},{"SPRITE":{"name":"0439","x":5587,"y":966,"w":94,"h":118,"rotated":false}},{"SPRITE":{"name":"0440","x":3798,"y":2483,"w":109,"h":80,"rotated":false}},{"SPRITE":{"name":"0441","x":610,"y":1337,"w":101,"h":70,"rotated":false}},{"SPRITE":{"name":"0442","x":4975,"y":2746,"w":126,"h":101,"rotated":false}},{"SPRITE":{"name":"0443","x":3280,"y":3621,"w":175,"h":237,"rotated":false}},{"SPRITE":{"name":"0444","x":3280,"y":3621,"w":175,"h":237,"rotated":false}},{"SPRITE":{"name":"0445","x":6888,"y":4203,"w":168,"h":176,"rotated":false}},{"SPRITE":{"name":"0446","x":6888,"y":4203,"w":168,"h":176,"rotated":false}},{"SPRITE":{"name":"0447","x":4626,"y":4206,"w":161,"h":180,"rotated":false}},{"SPRITE":{"name":"0448","x":4626,"y":4206,"w":161,"h":180,"rotated":false}},{"SPRITE":{"name":"0449","x":4626,"y":4206,"w":161,"h":180,"rotated":false}},{"SPRITE":{"name":"0450","x":4626,"y":4206,"w":161,"h":180,"rotated":false}},{"SPRITE":{"name":"0451","x":4626,"y":4206,"w":161,"h":180,"rotated":false}},{"SPRITE":{"name":"0452","x":6072,"y":4215,"w":165,"h":165,"rotated":false}},{"SPRITE":{"name":"0453","x":6072,"y":4215,"w":165,"h":165,"rotated":false}},{"SPRITE":{"name":"0454","x":8034,"y":1709,"w":156,"h":153,"rotated":false}},{"SPRITE":{"name":"0455","x":7002,"y":0,"w":840,"h":616,"rotated":false}},{"SPRITE":{"name":"0456","x":7002,"y":0,"w":840,"h":616,"rotated":false}},{"SPRITE":{"name":"0457","x":712,"y":901,"w":817,"h":629,"rotated":false}},{"SPRITE":{"name":"0458","x":712,"y":901,"w":817,"h":629,"rotated":false}},{"SPRITE":{"name":"0459","x":7002,"y":616,"w":811,"h":636,"rotated":false}},{"SPRITE":{"name":"0460","x":7002,"y":616,"w":811,"h":636,"rotated":false}},{"SPRITE":{"name":"0461","x":7002,"y":616,"w":811,"h":636,"rotated":false}},{"SPRITE":{"name":"0462","x":7002,"y":616,"w":811,"h":636,"rotated":false}},{"SPRITE":{"name":"0463","x":7002,"y":616,"w":811,"h":636,"rotated":false}},{"SPRITE":{"name":"0464","x":5684,"y":0,"w":776,"h":674,"rotated":false}},{"SPRITE":{"name":"0465","x":5684,"y":0,"w":776,"h":674,"rotated":false}},{"SPRITE":{"name":"0466","x":3939,"y":3594,"w":435,"h":281,"rotated":false}},{"SPRITE":{"name":"0467","x":4541,"y":1652,"w":580,"h":635,"rotated":false}},{"SPRITE":{"name":"0468","x":3912,"y":2236,"w":536,"h":637,"rotated":false}},{"SPRITE":{"name":"0469","x":3912,"y":2236,"w":536,"h":637,"rotated":false}}]},"meta":{"app":"Adobe Animate","version":"18.0.2.126","image":"spritemap.png","format":"RGBA8888","size":{"w":8192,"h":8192},"scale":"1"}}